Metadata-Version: 2.1
Name: Mongo-db-operations
Version: 0.0.1
Summary: Mongo DB Operation
Home-page: UNKNOWN
Author: Harish Musti
License: MIT
Download-URL: https://github.com/hareshkm999/mongopi/archive/refs/tags/0.0.1.tar.gz
Platform: UNKNOWN
License-File: LICENSE.txt
